commonmarkslack/__init__.py
commonmarkslack/render/__init__.py
commonmarkslack/render/plaintext.py
commonmarkslack/render/slack.py
commonmark_slack-1.0.0.dist-info/LICENSE
commonmark_slack-1.0.0.dist-info/METADATA
commonmark_slack-1.0.0.dist-info/WHEEL
commonmark_slack-1.0.0.dist-info/top_level.txt
commonmark_slack-1.0.0.dist-info/RECORD
