Metadata-Version: 2.1
Name: commonmark-slack
Version: 1.0.0
Summary: Convert CommonMark Markdown to Slack Markdown
Home-page: https://github.com/klm1/commonmarkslack
Author: Ken Morse
License: MIT
Platform: UNKNOWN
Classifier: License :: OSI Approved :: MIT License
Classifier: Programming Language :: Python
Classifier: Programming Language :: Python :: 3
Classifier: Topic :: Software Development :: Libraries :: Python Modules
Classifier: Topic :: Text Processing :: Markup
Classifier: Topic :: Text Processing :: Markup :: Markdown
Classifier: Topic :: Utilities
Requires-Python: >3.6.0
Requires-Dist: commonmark
